[
  {
    "title": "NOW THIS POLICY WITNESSETH that subject to the terms,",
    "deductible": null,
    "waiting_period": null,
    "is_exclusion": true,
    "sample_text": "conditions and exclusions herein contained or endorsed or \notherwise expressed herein, to indemnify the Insured or \nOwner against the statutory liability arising out of accidents \noccurring during the currency of the policy due to handling \nof hazardous substances as provided for in the said Act \nand the Rules framed thereunder."
  },
  {
    "title": "3. \t EXCLUSIONS",
    "deductible": null,
    "waiting_period": null,
    "is_exclusion": true,
    "sample_text": "The Company shall not be liable:\n\t\n(i)\t\nfor any willful or intentional non-compliance of any \nstatutory requirements;\n\t\n(ii)\t\nin respect of fines, penalties, punitive and /or \nexemplary damages;\n\t\n(iii)\t under any law or legislation except in so far as \nprovided for in Section 8 (1) & 8(2) of the Act;\n\t\n(iv)\t in respect of damage to property owned, leased or \nhired or under hire purchase or on loan to the Insured \nor otherwise in the Insured or Owner\u2019s control, care \nor custody;\n\t\n(v)\t for any liability directly or indirectly occasioned \nby, happening through or inconsequence of war, \ninvasion"
  }
]